SystemScripter/__init__.py
SystemScripter/dates.py
SystemScripter-0.1.1.dist-info/LICENSE
SystemScripter-0.1.1.dist-info/METADATA
SystemScripter-0.1.1.dist-info/WHEEL
SystemScripter-0.1.1.dist-info/top_level.txt
SystemScripter-0.1.1.dist-info/RECORD
