Metadata-Version: 2.1
Name: SystemScripter
Version: 0.1.1
Summary: Package made to script for windows system and get system info
Home-page: https://github.com/Ixonblitz-MatOS/SystemScripter
Author: Ixonblitz-MatOS
Author-email: gavellmathew@gmail.com
License: UNKNOWN
Project-URL: Bug Tracker, https://github.com/Ixonblitz-MatOS/SystemScripter/issues
Platform: UNKNOWN
Classifier: Programming Language :: Python :: 3
Classifier: License :: OSI Approved :: MIT License
Classifier: Operating System :: Microsoft :: Windows :: Windows 10
Requires-Python: >=3.10
License-File: LICENSE
